sigaa/__init__.py
sigaa/api.py
sigaa/exceptions.py
sigaa/mailbox.py
sigaa/util.py
sigaa/exceptions/__init__.py
sigaa/exceptions/exceptions.py
sigaa_cli-0.8.0.dist-info/LICENSE
sigaa_cli-0.8.0.dist-info/METADATA
sigaa_cli-0.8.0.dist-info/WHEEL
sigaa_cli-0.8.0.dist-info/top_level.txt
sigaa_cli-0.8.0.dist-info/RECORD
