Metadata-Version: 2.1
Name: sigaa-cli
Version: 0.8.0
Summary: A uniffical Comand Line Interface that enable developers to execute some actions inside the SIGAA platform using python code. Independent of the university.
Home-page: https://github.com/macielti/sigaa-cli
Author: Bruno do Nascimento Maciel
Author-email: brunodonascimentomaciel@gmail.com
License: UNKNOWN
Platform: UNKNOWN
Classifier: Programming Language :: Python :: 3
Classifier: Development Status :: 2 - Pre-Alpha
Classifier: License :: OSI Approved :: GNU General Public License v3 or later (GPLv3+)
Classifier: Operating System :: OS Independent
Requires-Dist: requests
Requires-Dist: tqdm
